delete_migration_roosevelt/__init__.py
delete_migration_roosevelt/management.py
delete_migrations-1.0.2.dist-info/LICENSE.txt
delete_migrations-1.0.2.dist-info/METADATA
delete_migrations-1.0.2.dist-info/WHEEL
delete_migrations-1.0.2.dist-info/top_level.txt
delete_migrations-1.0.2.dist-info/RECORD
