Metadata-Version: 2.1
Name: delete-migrations
Version: 1.0.2
Summary: This is a command-line app that deletes a single folder migrations or all directory migrations folder
Home-page: https://github.com/RooseveltTech/delete_migration
Author: Abandy Roosevelt
Author-email: Abandy Roosevelt <rooseveltabandy@gmail.com>
Project-URL: Homepage, https://github.com/RooseveltTech/delete_migration
Project-URL: Bug Tracker, https://github.com/RooseveltTech/delete_migration/issues
Classifier: Programming Language :: Python :: 3
Classifier: License :: OSI Approved :: MIT License
Classifier: Operating System :: OS Independent
Requires-Python: >=3.6
License-File: LICENSE.txt
